PatchWorkPlot.py
patchworkplot-1.0.0.dist-info/licenses/LICENSE
py/.gitignore
py/config_utils.py
py/data_utils.py
py/paf_utils.py
py/tool_builder.py
py/utils.py
py/visualization_utils.py
patchworkplot-1.0.0.dist-info/METADATA
patchworkplot-1.0.0.dist-info/WHEEL
patchworkplot-1.0.0.dist-info/entry_points.txt
patchworkplot-1.0.0.dist-info/top_level.txt
patchworkplot-1.0.0.dist-info/RECORD
