Metadata-Version: 2.4
Name: PatchWorkPlot
Version: 1.0.0
Summary: A tool for visualization of pairwise alignments of multiple sequences
Requires-Python: >=3.7
License-File: LICENSE
Requires-Dist: pandas<3.0,>=2.2
Requires-Dist: biopython<2.0,>=1.85
Requires-Dist: matplotlib<4.0,>=3.10
Requires-Dist: seaborn<0.14,>=0.13
Requires-Dist: numpy<2.0,>=1.24
Dynamic: license-file
